README.md
setup.py
./probable_happiness/Client.py
./probable_happiness/__init__.py
./probable_happiness/kugou/__init__.py
./probable_happiness/kugou/api.py
probable_happiness.egg-info/PKG-INFO
probable_happiness.egg-info/SOURCES.txt
probable_happiness.egg-info/dependency_links.txt
probable_happiness.egg-info/requires.txt
probable_happiness.egg-info/top_level.txt